NAPDAMESH/__init__.py
NAPDAMESH/__main__.py
NAPDAMESH/base.py
NAPDAMESH/boolean.py
NAPDAMESH/bounds.py
NAPDAMESH/caching.py
NAPDAMESH/collision.py
NAPDAMESH/comparison.py
NAPDAMESH/constants.py
NAPDAMESH/convex.py
NAPDAMESH/creation.py
NAPDAMESH/curvature.py
NAPDAMESH/decomposition.py
NAPDAMESH/exceptions.py
NAPDAMESH/geometry.py
NAPDAMESH/graph.py
NAPDAMESH/grouping.py
NAPDAMESH/inertia.py
NAPDAMESH/intersections.py
NAPDAMESH/interval.py
NAPDAMESH/iteration.py
NAPDAMESH/nsphere.py
NAPDAMESH/parent.py
NAPDAMESH/permutate.py
NAPDAMESH/points.py
NAPDAMESH/poses.py
NAPDAMESH/primitives.py
NAPDAMESH/proximity.py
NAPDAMESH/py.typed
NAPDAMESH/registration.py
NAPDAMESH/remesh.py
NAPDAMESH/rendering.py
NAPDAMESH/repair.py
NAPDAMESH/resolvers.py
NAPDAMESH/sample.py
NAPDAMESH/schemas.py
NAPDAMESH/smoothing.py
NAPDAMESH/transformations.py
NAPDAMESH/triangles.py
NAPDAMESH/typed.py
NAPDAMESH/units.py
NAPDAMESH/util.py
NAPDAMESH/version.py
NAPDAMESH/resources/creation.json
NAPDAMESH/resources/units_to_inches.json
NAPDAMESH/resources/schema/README.md
NAPDAMESH/resources/schema/gltf2.schema.zip
NAPDAMESH/resources/schema/urdf.xsd
NAPDAMESH/resources/schema/primitive/box.schema.json
NAPDAMESH/resources/schema/primitive/capsule.schema.json
NAPDAMESH/resources/schema/primitive/cylinder.schema.json
NAPDAMESH/resources/schema/primitive/extrusion.schema.json
NAPDAMESH/resources/schema/primitive/primitive.schema.json
NAPDAMESH/resources/schema/primitive/scenegraph.schema.json
NAPDAMESH/resources/schema/primitive/sphere.schema.json
NAPDAMESH/resources/schema/primitive/transform.schema.json
NAPDAMESH/resources/schema/primitive/trimesh.schema.json
NAPDAMESH/resources/schema/primitive/wkt.polygon.schema.json
NAPDAMESH/resources/templates/base.svg
NAPDAMESH/resources/templates/blender_boolean.py.tmpl
NAPDAMESH/resources/templates/blender_unwrap.py.template
NAPDAMESH/resources/templates/dxf.json
NAPDAMESH/resources/templates/path.svg
NAPDAMESH/resources/templates/ply.json
napdamesh-0.1.0.dist-info/METADATA
napdamesh-0.1.0.dist-info/WHEEL
napdamesh-0.1.0.dist-info/top_level.txt
napdamesh-0.1.0.dist-info/RECORD
